Counter.v
/**
 * Universidad de Costa Rica
 * Escuela de Ingeniería Eléctrica
 * Circuitos Digitales I - IE0323
 * Proyecto Verilog
 *
 * archivo: Counter.v
 * autores:
 * Sergio Garino Vargas - B73157
 * Johan - 
 *
 * Descripción: 
 * Modulo Counter capaz de contar de 0 a 3 con base en un contador de 4 bits 
 */

/**
* Contador de 4 bits, sincronico, con habilitador y entrada de 
* datos paralela y salida de Ripple Carry Out (rco)
* Ademas, posee una entrada de 2 bits para elegir el modo de 
* funcionamiento del contador, de la siguiente forma:
*
* Modo    Descripcion
* 0 : Cuenta ascendente de 1 en 1. RC0 = 1 cuando Q = 15
* 1 : Carga de Datos Paralela. Permite inicializar el contador 
*     en una cuenta particular.
**/

// Módulo para un contador de 4 bits con carga paralela y habilitador
module Counter_4bits(
	input wire clk, enb, rst,
	input wire modo,
	input wire [3:0] data, 
	output reg [3:0] Q
);

always @(posedge clk)
begin
	
	if (enb)
	begin
    case(modo)
        // Modo conteo
        0: begin
            if (~rst)
            begin
                Q <= 0;
            end
            else
            begin
                Q <= Q + 1;
            end
        end 

        // Modo carga paralela
        1: begin
            Q <= data;		// Inicializar mi contador con el valor de data.
        end
    
        default: begin
            Q <= Q + 1;
        end
    
    endcase
	end
	
end

endmodule


// Módulo para una compuerta lógica NAND de 2 entradas
module NAND(
    input a, // Entrada A
    input b, // Entrada B
    output y // Salida Y
);
    assign y = ~(a & b); // La salida Y es el resultado de aplicar la operación NAND a las entradas A y B
endmodule


module Counter(
    input clk, enb, // Señal de reloj, enable y reset
    input modo,
    input [3:0] data, // Valor de carga paralela
    output [3:0] Q // Salida del contador de 4 bits
);

    wire nand_a;
    wire nand_b;
    wire nand_out_rst;

    assign nand_a = Q[0];
    assign nand_b = Q[1];

    // Instancia del módulo Counter_4bits
    Counter_4bits counter_4bits(
        .clk(clk), // entrada
        .enb(enb), // entrada
        .rst(nand_out_rst),
        .modo(modo),
        .data(data),
        .Q(Q)
    );    

    // Instancia del módulo NAND
    NAND nand_inst(
        .a(nand_a), // La entrada A es el bit 1 de la salida del contador
        .b(nand_b), // La entrada B es el bit 0 de la salida del contador
        .y(nand_out_rst)); // La salida se conecta a nand_out
endmodule

Counter_Tests.v
/**
 * Universidad de Costa Rica
 * Escuela de Ingeniería Eléctrica
 * Circuitos Digitales I - IE0323
 * Proyecto Verilog
 *
 * archivo: asm_ascensor.v
 * autores:
 * Sergio Garino Vargas - B73157
 * Johan - 
 *
 * Descripción: 
 * Test bench para el módulo Counter
 */
module Test_bench(
	output reg clk, enb,
	output reg modo,
	output reg [3:0] data,
	input wire [3:0] Q);
	
	//Defino el reloj 
	initial clk = 0; 
	always #1 clk = ~clk;

	initial
	begin

	    $dumpfile("contador4.vcd");
	    $dumpvars;

		//Prubas para el contador de 4 bits

	    // Prueba 1 - Cuenta Ascendente 
        modo    = 1;
		#3 enb  = 1;
		#1 data = 0;
		#3 modo = 0;
		#50 enb = 0;        	
		
		#10 $finish;
		
	end 

endmodule

Counter_Tests_probador.v
/**
 * Universidad de Costa Rica
 * Escuela de Ingeniería Eléctrica
 * Circuitos Digitales I - IE0323
 * Proyecto Verilog
 *
 * archivo: asm_ascensor.v
 * autores:
 * Sergio Garino Vargas - B73157
 * Johan - 
 *
 * Descripción: 
 * Test bench para el módulo Counter
 */


`include "Counter.v"
`include "Counter_Tests.v"

/*
* probador
* Agrega conexiones entre el UUT (contador de 4 bits) y su testbench.
*/
module probador();

	wire clk, enb;
	wire modo;
	wire [3:0] data, Q;

    Test_bench signals_generator(.clk(clk), .enb(enb), .modo(modo), .data(data), .Q(Q));
    Counter UUT(.clk(clk), .enb(enb), .modo(modo), .data(data), .Q(Q));

endmodule

contador4.vcd
$date
	Fri Jul  7 05:47:38 2023
$end
$version
	Icarus Verilog
$end
$timescale
	1s
$end
$scope module probador $end
$var wire 1 ! modo $end
$var wire 1 " enb $end
$var wire 4 # data [3:0] $end
$var wire 1 $ clk $end
$var wire 4 % Q [3:0] $end
$scope module UUT $end
$var wire 1 & nand_out_rst $end
$var wire 1 ' nand_b $end
$var wire 1 ( nand_a $end
$var wire 1 ! modo $end
$var wire 1 " enb $end
$var wire 4 ) data [3:0] $end
$var wire 1 $ clk $end
$var wire 4 * Q [3:0] $end
$scope module counter_4bits $end
$var wire 1 & rst $end
$var wire 1 ! modo $end
$var wire 1 " enb $end
$var wire 4 + data [3:0] $end
$var wire 1 $ clk $end
$var reg 4 , Q [3:0] $end
$upscope $end
$scope module nand_inst $end
$var wire 1 ( a $end
$var wire 1 ' b $end
$var wire 1 & y $end
$upscope $end
$upscope $end
$scope module signals_generator $end
$var wire 4 - Q [3:0] $end
$var reg 1 $ clk $end
$var reg 4 . data [3:0] $end
$var reg 1 " enb $end
$var reg 1 ! modo $end
$upscope $end
$upscope $end
$enddefinitions $end
#0
$dumpvars
bx .
bx -
bx ,
bx +
bx *
bx )
x(
x'
x&
bx %
0$
bx #
x"
1!
$end
#1
1$
#2
0$
#3
1$
1"
#4
0$
b0 #
b0 )
b0 +
b0 .
#5
1&
0'
0(
b0 %
b0 *
b0 ,
b0 -
1$
#6
0$
#7
1(
b1 %
b1 *
b1 ,
b1 -
1$
0!
#8
0$
#9
1'
0(
b10 %
b10 *
b10 ,
b10 -
1$
#10
0$
#11
0&
1(
b11 %
b11 *
b11 ,
b11 -
1$
#12
0$
#13
1&
0'
0(
b0 %
b0 *
b0 ,
b0 -
1$
#14
0$
#15
1(
b1 %
b1 *
b1 ,
b1 -
1$
#16
0$
#17
1'
0(
b10 %
b10 *
b10 ,
b10 -
1$
#18
0$
#19
0&
1(
b11 %
b11 *
b11 ,
b11 -
1$
#20
0$
#21
1&
0'
0(
b0 %
b0 *
b0 ,
b0 -
1$
#22
0$
#23
1(
b1 %
b1 *
b1 ,
b1 -
1$
#24
0$
#25
1'
0(
b10 %
b10 *
b10 ,
b10 -
1$
#26
0$
#27
0&
1(
b11 %
b11 *
b11 ,
b11 -
1$
#28
0$
#29
1&
0'
0(
b0 %
b0 *
b0 ,
b0 -
1$
#30
0$
#31
1(
b1 %
b1 *
b1 ,
b1 -
1$
#32
0$
#33
1'
0(
b10 %
b10 *
b10 ,
b10 -
1$
#34
0$
#35
0&
1(
b11 %
b11 *
b11 ,
b11 -
1$
#36
0$
#37
1&
0'
0(
b0 %
b0 *
b0 ,
b0 -
1$
#38
0$
#39
1(
b1 %
b1 *
b1 ,
b1 -
1$
#40
0$
#41
1'
0(
b10 %
b10 *
b10 ,
b10 -
1$
#42
0$
#43
0&
1(
b11 %
b11 *
b11 ,
b11 -
1$
#44
0$
#45
1&
0'
0(
b0 %
b0 *
b0 ,
b0 -
1$
#46
0$
#47
1(
b1 %
b1 *
b1 ,
b1 -
1$
#48
0$
#49
1'
0(
b10 %
b10 *
b10 ,
b10 -
1$
#50
0$
#51
0&
1(
b11 %
b11 *
b11 ,
b11 -
1$
#52
0$
#53
1&
0'
0(
b0 %
b0 *
b0 ,
b0 -
1$
#54
0$
#55
1(
b1 %
b1 *
b1 ,
b1 -
1$
#56
0$
#57
1$
0"
