Elevator.v
/**
 * Universidad de Costa Rica
 * Escuela de Ingeniería Eléctrica
 * Circuitos Digitales I - IE0323
 * Proyecto Verilog
 *
 * archivo: asm_ascensor.v
 * autores:
 * Sergio Garino Vargas - B73157
 * Johan Herrera Chaves - C03811
 *
 * Descripción: 
 * En este archivo se tiene la implemetación del Diagrama ASM del 
 * ascensor.
 */

/** IMPORTANTE!!!!!!!!!!
* Para correr este tench se deben de poner los siguientes comandos en una
* terminal Linux que tenga instalada iverilog, vvp y gtkwave
***************************************************
iverilog -o ElevadorPrueba Elevator_Tests.v
vvp ElevadorPrueba
gtkwave Elevator.vcd
***************************************************
**/


module Elevator (
    input Clk, Reset, /**< Entradas de Clock y Reset */
    input I0, I1, I2, /**< Botones internos */
    input E0, E1, E2, /**< Botones externos */
    input S0, S1, S2, /**< Sensores de posición */ 
    input R, /**< Señal que se pone en alto cuando el tiempo para tener la puerta abierta expiró */
    output M, D, /**< Bits para controlar el (M)otor a activar y la (D)irección */ 
    output P, W, /**< Bits para regular la velocidad de los 2 motores mediante PWM*/
    output S); /**< Sonido que se activa antes de abrir la puerta */
    /**
     * Se definen dos vectores, uno de estado presente y otro para el próximo 
     * estado los cuales son de 4 cuatro por que el diseño de la ASM se
     * tiene 14 estados posibles que son requesentables con 4 bits.
     */

    reg [3:0] estadoPresente, proximoEstado;

    /**
     * Se asignan los estados con base en el ASM
     */
    parameter a = 4'b0000; // 0
    parameter b = 4'b0001; // 1
    parameter c = 4'b0010; // 2
    parameter d = 4'b0011; // 3
    parameter e = 4'b1100; // C
    parameter f = 4'b0100; // 4
    parameter g = 4'b0101; // 5
    parameter h = 4'b0110; // 6
    parameter i = 4'b0111; // 7
    parameter j = 4'b1000; // 8
    parameter k = 4'b1001; // 9
    parameter p = 4'b1010; // A
    parameter u = 4'b1011; // B
    parameter t = 4'b1101; // D

    /**
     * La memoria de estados
     */

    always @(posedge Clk, posedge Reset)
    begin
        if (Reset) estadoPresente <= a;
        else       estadoPresente <= proximoEstado;
    end

    /**
     * Cálculo de lógica de próximo estados: mediante una sentencia always se
     * determina el siguiente estado partiendo de cada uno de los estados
     */

    always @(*)
    begin
        case (estadoPresente)
        // Partiendo del estado a
        a:
        casez({S0, S1, S2})
            3'b1??: proximoEstado = b;
            3'b01?: proximoEstado = c;
            3'b001: proximoEstado = d;
            3'b000: proximoEstado = a;
        endcase
        // Partiendo del estado b
        b:
        casez ({E0, I2, E2, E1, I1})
            5'b1????: proximoEstado = p; 
            5'b01???: proximoEstado = f;
            5'b001??: proximoEstado = f;
            5'b0001?: proximoEstado = h;
            5'b00001: proximoEstado = h;
            5'b00000: proximoEstado = b;
        endcase
        // Partiendo del estado c
        c:
        casez ({E1, I2, E2, I0, E0})
            5'b1????: proximoEstado = p;
            5'b01???: proximoEstado = i;
            5'b001??: proximoEstado = i;
            5'b0001?: proximoEstado = j;
            5'b00001: proximoEstado = j;
            5'b00000: proximoEstado = c;
        endcase
        // Partiendo del estado d
        d:
        casez ({E2, I0, E0, E1, I1})
            5'b1????: proximoEstado = p;
            5'b01???: proximoEstado = g;
            5'b001??: proximoEstado = g;
            5'b0001?: proximoEstado = k;
            5'b00001: proximoEstado = k;
            5'b00000: proximoEstado = d;
        endcase
        // Partiendo del estado e
        e:
        begin
            if (R) proximoEstado = t;
            else proximoEstado = e;
        end
        // Partiendo del estado f
        f:
        begin
            if (S1) proximoEstado = i;
            else proximoEstado = f;
        end
        // Partiendo del estado g
        g:
        begin
            if (S1) proximoEstado = j;
            else proximoEstado = g;
        end
        // Partiendo del estado h
        h:
        begin
            if (S1) proximoEstado = p;
            else proximoEstado = h;
        end
        // Partiendo del estado y
        i:
        begin
            if (S2) proximoEstado = p;
            else proximoEstado = i;
        end
        // Partiendo del estado j
        j:
        begin
            if (S0) proximoEstado = p;
            else proximoEstado = j;
        end
        // Partiendo del estado k
        k:
        begin
            if (S1) proximoEstado = p;
            else proximoEstado = k;
        end
        // Partiendo del estado p, la transicón es incondicional al estado u
        p:
            proximoEstado = u;
        // Partiendo del estado u
        u:
            proximoEstado = e;
        // Partiendo del estado t
        t:
            proximoEstado = a;
        endcase
    end

    /**
     * La lógica de cálculo de salidas permite activar las salidas
     */
    /**
     * Las salidas M y D funcionan de la siguiente manera
     * (MD): Motor, dirección
     * (00): Motor 0, bajar
     * (01): Motor 0, subir
     * (10): Motor 1, cerrar
     * (11): Motor 1, abrir
     *
     * Las salidas P y W funcionan de la siguiente manera:
     * (PW): Velocidad, Ciclo de trabajo
     * (00): Detenido, Ciclo de trabajo = 25%
     * (01): Lento, Ciclo de trabajo = 25%
     * (10): Medio, Ciclo de trabajo = 50%
     * (11): Rápido, Ciclo de trabajo = 75%
     * 
     * La salida S se activa antes de abrir la puerta
     */
    assign M = (estadoPresente == u | estadoPresente == t); 

    assign D = (estadoPresente == f | 
                estadoPresente == h | 
                estadoPresente == i | 
                estadoPresente == u);

    assign P = (estadoPresente == f | 
                estadoPresente == g | 
                estadoPresente == h | 
                estadoPresente == i | 
                estadoPresente == j | 
                estadoPresente == k);

    assign W = (estadoPresente == f | 
                estadoPresente == g | 
                estadoPresente == u | 
                estadoPresente == t);

    assign S = (estadoPresente == p);

endmodule

Elevator_Tests.v
/**
 * Universidad de Costa Rica
 * Escuela de Ingeniería Eléctrica
 * Circuitos Digitales I - IE0323
 * Proyecto Verilog
 *
 * archivo: asm_ascensor.v
 * autores:
 * Sergio Garino Vargas - B73157
 * Johan - 
 *
 * Descripción: 
 * Test bench para el módulo Elevator
 */

`timescale 1ps/1ps
`include "Elevator.v"

module Elevator_Tester;

    /**
    * Se definen como reg lo que la máquina recibe como entradas
    **/
    reg Clk, Reset;
    reg I0, I1, I2;
    reg E0, E1, E2;
    reg S0, S1, S2;
    reg R;

    /**
    * Se definen como wires lo que la máquina da como salidas
    **/
    wire M, D;
    wire P, W;
    wire S;

    /**
    * Se definen los vectores de pruebas cada uno de ellos tiene tamaño 10
    * debido a que se tienen las 10 entradas I0, I1, I2, E0, E1, E2,S0, S1,
    * S2 y R, la cantidad de vectores depende del número de pruebas que se
    * deseen realizar, en este caso se hacen X pruebas
    **/
    reg [9:0] testvectors [6:0];
    integer vectornum;

    /**
    * Se realiza una instanción nombrada del módulo Elevator bajo el nombre de
    * uut
    **/
    Elevator uut (
        .Clk(Clk), .Reset(Reset),
        .I0(I0), .I1(I1), .I2(I2),
        .E0(E0), .E1(E1), .E2(E2),
        .S0(S0), .S1(S1), .S2(S2),
        .R(R));

    /**
    * Estas son las pruebas que se le realizan a la máquina, el orden de las
    * entradas es:
    * I0, I1, I2, E0, E1, E2, S0, S1, S2, R
    **/
    initial
    begin
        testvectors[0] = 10'b0001_1111_11;

        vectornum = 0;

        Reset = 1;
        #3 Reset = 0;

        $dumpfile("Elevator.vcd");
        $dumpvars;
    end
    
    /**
    * Se define la señal de reloj
    **/

    always
    begin
        Clk = 1; #5; Clk = 0; #5;  
    end

    always @(posedge Clk)
    begin
    #1 if (!Reset)
        begin
            $display ("Las salidas son M=%b, D=%b, P=%b, W=%b, S=%b", M, D, P, W, S);
            vectornum = vectornum + 1;
                if (vectornum == 7/*Cantidad de pruebas*/)
                begin
                    $finish;
                end
        end
    end
endmodule

Elevator.vcd
$date
	Fri Jul  7 23:38:18 2023
$end
$version
	Icarus Verilog
$end
$timescale
	1s
$end
$scope module Elevator_Tester $end
$var wire 1 ! D $end
$var wire 1 " M $end
$var wire 1 # P $end
$var wire 1 $ S $end
$var wire 1 % W $end
$var reg 1 & Clk $end
$var reg 1 ' E0 $end
$var reg 1 ( E1 $end
$var reg 1 ) E2 $end
$var reg 1 * I0 $end
$var reg 1 + I1 $end
$var reg 1 , I2 $end
$var reg 1 - R $end
$var reg 1 . Reset $end
$var reg 1 / S0 $end
$var reg 1 0 S1 $end
$var reg 1 1 S2 $end
$var integer 32 2 vectornum [31:0] $end
$scope module uut $end
$var wire 1 & Clk $end
$var wire 1 3 D $end
$var wire 1 ' E0 $end
$var wire 1 ( E1 $end
$var wire 1 ) E2 $end
$var wire 1 * I0 $end
$var wire 1 + I1 $end
$var wire 1 , I2 $end
$var wire 1 4 M $end
$var wire 1 5 P $end
$var wire 1 - R $end
$var wire 1 . Reset $end
$var wire 1 / S0 $end
$var wire 1 0 S1 $end
$var wire 1 1 S2 $end
$var wire 1 6 W $end
$var wire 1 7 S $end
$var reg 4 8 estadoPresente [3:0] $end
$var reg 4 9 proximoEstado [3:0] $end
$upscope $end
$upscope $end
$enddefinitions $end
#8
$dumpvars
b0 9
b0 8
07
06
05
04
03
b0 2
01
00
0/
0.
0-
0,
0+
0*
0)
0(
0'
0&
z%
z$
z#
z"
z!
$end
#10
1&
#11
b1 2
#15
0&
#20
1&
#21
b10 2
#25
b1 9
1/
0&
#30
b1 8
1&
#31
b11 2
#35
b1010 9
1'
0/
0&
#40
b1011 9
17
b1010 8
1&
#41
b100 2
#45
0'
0&
#50
16
b1100 9
14
13
07
b1011 8
1&
#51
b101 2
#55
0&
#60
06
04
03
b1100 8
1&
#61
b110 2
#65
0&
#70
1&
#71
b111 2
#75
b1101 9
1-
0&
#80
b0 9
14
16
b1101 8
1&
#81
b1000 2
#85
0&
#90
04
06
b0 8
1&
#91
b1001 2
#95
b1 9
1/
0-
0&
#100
b1 8
1&
#101
b1010 2
#105
b100 9
1,
0/
0&
#110
15
13
16
b100 8
1&
#111
b1011 2
#115
0,
0&
#120
1&
#121
b1100 2
#125
0&
#130
1&
#131
b1101 2
#135
b111 9
10
0&
#140
06
b111 8
1&
#141
b1110 2
#145
00
0&
#150
1&
#151
b1111 2
#155
0&
#160
1&
#161
b10000 2
#165
b1010 9
11
0&
#170
05
03
b1011 9
17
b1010 8
1&
#171
b10001 2
#175
01
1-
0&
#180
16
b1100 9
14
13
07
b1011 8
1&
#181
b10010 2
#185
0&
#190
06
b1101 9
04
03
b1100 8
1&
#191
b10011 2
#195
0&
#200
b0 9
14
16
b1101 8
1&
#201
b10100 2
#205
1/
0-
0&
#210
b1 9
04
06
b0 8
1&
#211
b10101 2
#215
0&
#220
b1 8
1&
#221
b10110 2
#225
0/
0&
#230
1&
#231
b10111 2
#235
0&
#240
1&
#241
b11000 2
#245
b110 9
1(
0&
#250
15
13
b110 8
1&
#251
b11001 2
#255
0(
0&
#260
1&
#261
b11010 2
#265
0&
#270
1&
#271
b11011 2
#275
b1010 9
10
0&
#280
05
03
b1011 9
17
b1010 8
1&
#281
b11100 2
#285
00
1-
0&
#290
16
b1100 9
14
13
07
b1011 8
1&
#291
b11101 2
#295
0&
#300
06
b1101 9
04
03
b1100 8
1&
#301
b11110 2
#305
0&
#310
b0 9
14
16
b1101 8
1&
#311
b11111 2
#315
10
0-
0&
#320
b10 9
04
06
b0 8
1&
#321
b100000 2
#325
0&
#330
b10 8
1&
#331
b100001 2
#335
00
0&
#340
1&
#341
b100010 2
#345
0&
#350
1&
#351
b100011 2
#355
b1000 9
1*
0&
#360
15
b1000 8
1&
#361
b100100 2
#365
b1010 9
0*
1/
0&
#370
05
b1011 9
17
b1010 8
1&
#371
b100101 2
#375
0/
1-
0&
#380
16
b1100 9
14
13
07
b1011 8
1&
#381
b100110 2
#385
0&
#390
06
b1101 9
04
03
b1100 8
1&
#391
b100111 2
#395
0&
#400
b0 9
14
16
b1101 8
1&
#401
b101000 2
#405
0-
0&
#410
04
06
b0 8
1&
#411
b101001 2
#415
x*
x+
x,
x'
x(
x)
x/
x0
x1
x-
0&
#420
1&
#421
b101010 2
