pruebaSolo4bits/Counter.v
/**
 * Universidad de Costa Rica
 * Escuela de Ingeniería Eléctrica
 * Circuitos Digitales I - IE0323
 * Proyecto Verilog
 *
 * archivo: Counter.v
 * autores:
 * Sergio Garino Vargas - B73157
 * Johan - 
 *
 * Descripción: 
 * Modulo Counter capaz de contar de 0 a 3 con base en un contador de 4 bits 
 */

/**
* Contador de 4 bits, sincronico, con habilitador y entrada de 
* datos paralela y salida de Ripple Carry Out (rco)
* Ademas, posee una entrada de 2 bits para elegir el modo de 
* funcionamiento del contador, de la siguiente forma:
*
* Modo    Descripcion
* 0 : Cuenta ascendente de 1 en 1. RC0 = 1 cuando Q = 15
* 1 : Carga de Datos Paralela. Permite inicializar el contador 
*     en una cuenta particular.
**/

// Módulo para un contador de 4 bits con carga paralela y habilitador
module counter4(
	input wire clk, enb, rst,
	input wire modo,
	input wire [3:0] data, 
	output reg [3:0] Q
);

always @(posedge clk, negedge rst)
begin
	
	if (enb)
	begin
		case(modo)
            // Modo conteo
			0: begin
                if (~rst)
                begin
                    Q <= 0;
                end
                else
                begin
                    Q <= Q + 1;
                end
			end 

            // Modo carga paralela
			1: begin
				Q <= data;		// Inicializar mi contador con el valor de data.
			end
		
			default: begin
				Q <= Q + 1;
			end
		
		endcase
	end
	
end
 
endmodule

/*
// Módulo para una compuerta lógica NAND de 2 entradas
module NAND(
    input a, // Entrada A
    input b, // Entrada B
    output y // Salida Y
);
    assign y = ~(a & b); // La salida Y es el resultado de aplicar la operación NAND a las entradas A y B
endmodule


module Counter(
    input clk, // Señal de reloj
    input rst, // Señal de reset activa en alto
    input en, // Señal de habilitador
    input [3:0] load, // Valor de carga paralela
    output [1:0] count // Salida del contador
);
    wire nand_out; // Salida del módulo NAND
    
    // Instancia del módulo Counter_4bits
    Counter_4bits counter_4bits(
        .clk(clk),
        .rst(rst),
        .en(en),
        .load(load),
        .count(count)
    );    


    // Instancia del módulo NAND
    NAND nand_inst(
        .a(count[1]), // La entrada A es el bit 1 de la salida del contador
        .b(count[0]), // La entrada B es el bit 0 de la salida del contador
        .y(nand_out) // La salida se conecta a nand_out
    );

    assign rst = nand_out; // La señal de reset se conecta a la salida del módulo NAND para resetear automáticamente el contador cuando llegue a 3 (11 en binario)

endmodule
*/

pruebaSolo4bits/Counter_Tests.v
/**
 * Universidad de Costa Rica
 * Escuela de Ingeniería Eléctrica
 * Circuitos Digitales I - IE0323
 * Proyecto Verilog
 *
 * archivo: asm_ascensor.v
 * autores:
 * Sergio Garino Vargas - B73157
 * Johan - 
 *
 * Descripción: 
 * Test bench para el módulo Counter
 */
module Test_bench(
	output reg clk, enb, rst,
	output reg modo,
	output reg [3:0] data,
	input wire [3:0] Q
	);
	
	//Defino el reloj 
	initial clk = 0; 
	always #1 clk = ~clk;

	
	initial
	begin

	    $dumpfile("contador4.vcd");
	    $dumpvars;

		//Prubas para el contador de 4 bits

	    // Prueba 1 - Cuenta Ascendente 
        modo    = 1;
        #1 rst  = 1;
		#1 enb  = 0;
		#3 enb  = 1;
		#1 data = 0;
		#3 modo = 0;
        #60 rst = 0;
        #10 rst = 1;
        #10 rst = 0;
        #10 rst = 1;
        #10 rst = 0;
        #10 rst = 1;

		#50 enb = 0;
		
	    // Prueba 4 - Carga paralela		
		modo    = 1;
		#5 enb  = 1;		
		#4 data = 6;
        #5 modo = 0;
		#30 enb = 0;
		#10 $finish;
		
	end 

endmodule

pruebaSolo4bits/Counter_Tests_probador.v
/**
 * Universidad de Costa Rica
 * Escuela de Ingeniería Eléctrica
 * Circuitos Digitales I - IE0323
 * Proyecto Verilog
 *
 * archivo: asm_ascensor.v
 * autores:
 * Sergio Garino Vargas - B73157
 * Johan - 
 *
 * Descripción: 
 * Test bench para el módulo Counter
 */


`include "Counter.v"
`include "Counter_Tests.v"

/*
* probador
* Agrega conexiones entre el UUT (contador de 4 bits) y su testbench.
*/
module probador();

	wire clk, enb, rst;
	wire modo;
	wire [3:0] data, Q;

Test_bench signals_generator(.clk(clk), .enb(enb), .rst(rst), .modo(modo), .data(data), .Q(Q));
counter4 UUT(.clk(clk), .enb(enb), .rst(rst), .modo(modo), .data(data), .Q(Q));

endmodule

pruebaSolo4bits/contador4.vcd
$date
	Fri Jul  7 02:56:24 2023
$end
$version
	Icarus Verilog
$end
$timescale
	1s
$end
$scope module probador $end
$var wire 1 ! rst $end
$var wire 1 " modo $end
$var wire 1 # enb $end
$var wire 4 $ data [3:0] $end
$var wire 1 % clk $end
$var wire 4 & Q [3:0] $end
$scope module UUT $end
$var wire 1 ! rst $end
$var wire 1 " modo $end
$var wire 1 # enb $end
$var wire 4 ' data [3:0] $end
$var wire 1 % clk $end
$var reg 4 ( Q [3:0] $end
$upscope $end
$scope module signals_generator $end
$var wire 4 ) Q [3:0] $end
$var reg 1 % clk $end
$var reg 4 * data [3:0] $end
$var reg 1 # enb $end
$var reg 1 " modo $end
$var reg 1 ! rst $end
$upscope $end
$upscope $end
$enddefinitions $end
#0
$dumpvars
bx *
bx )
bx (
bx '
bx &
0%
bx $
x#
1"
x!
$end
#1
1!
1%
#2
0#
0%
#3
1%
#4
0%
#5
1%
1#
#6
0%
b0 $
b0 '
b0 *
#7
b0 &
b0 (
b0 )
1%
#8
0%
#9
b1 &
b1 (
b1 )
1%
0"
#10
0%
#11
b10 &
b10 (
b10 )
1%
#12
0%
#13
b11 &
b11 (
b11 )
1%
#14
0%
#15
b100 &
b100 (
b100 )
1%
#16
0%
#17
b101 &
b101 (
b101 )
1%
#18
0%
#19
b110 &
b110 (
b110 )
1%
#20
0%
#21
b111 &
b111 (
b111 )
1%
#22
0%
#23
b1000 &
b1000 (
b1000 )
1%
#24
0%
#25
b1001 &
b1001 (
b1001 )
1%
#26
0%
#27
b1010 &
b1010 (
b1010 )
1%
#28
0%
#29
b1011 &
b1011 (
b1011 )
1%
#30
0%
#31
b1100 &
b1100 (
b1100 )
1%
#32
0%
#33
b1101 &
b1101 (
b1101 )
1%
#34
0%
#35
b1110 &
b1110 (
b1110 )
1%
#36
0%
#37
b1111 &
b1111 (
b1111 )
1%
#38
0%
#39
b0 &
b0 (
b0 )
1%
#40
0%
#41
b1 &
b1 (
b1 )
1%
#42
0%
#43
b10 &
b10 (
b10 )
1%
#44
0%
#45
b11 &
b11 (
b11 )
1%
#46
0%
#47
b100 &
b100 (
b100 )
1%
#48
0%
#49
b101 &
b101 (
b101 )
1%
#50
0%
#51
b110 &
b110 (
b110 )
1%
#52
0%
#53
b111 &
b111 (
b111 )
1%
#54
0%
#55
b1000 &
b1000 (
b1000 )
1%
#56
0%
#57
b1001 &
b1001 (
b1001 )
1%
#58
0%
#59
b1010 &
b1010 (
b1010 )
1%
#60
0%
#61
b1011 &
b1011 (
b1011 )
1%
#62
0%
#63
b1100 &
b1100 (
b1100 )
1%
#64
0%
#65
b1101 &
b1101 (
b1101 )
1%
#66
0%
#67
b1110 &
b1110 (
b1110 )
1%
#68
0%
#69
b0 &
b0 (
b0 )
1%
0!
#70
0%
#71
1%
#72
0%
#73
1%
#74
0%
#75
1%
#76
0%
#77
1%
#78
0%
#79
b1 &
b1 (
b1 )
1%
1!
#80
0%
#81
b10 &
b10 (
b10 )
1%
#82
0%
#83
b11 &
b11 (
b11 )
1%
#84
0%
#85
b100 &
b100 (
b100 )
1%
#86
0%
#87
b101 &
b101 (
b101 )
1%
#88
0%
#89
b0 &
b0 (
b0 )
1%
0!
#90
0%
#91
1%
#92
0%
#93
1%
#94
0%
#95
1%
#96
0%
#97
1%
#98
0%
#99
b1 &
b1 (
b1 )
1%
1!
#100
0%
#101
b10 &
b10 (
b10 )
1%
#102
0%
#103
b11 &
b11 (
b11 )
1%
#104
0%
#105
b100 &
b100 (
b100 )
1%
#106
0%
#107
b101 &
b101 (
b101 )
1%
#108
0%
#109
b0 &
b0 (
b0 )
1%
0!
#110
0%
#111
1%
#112
0%
#113
1%
#114
0%
#115
1%
#116
0%
#117
1%
#118
0%
#119
b1 &
b1 (
b1 )
1%
1!
#120
0%
#121
b10 &
b10 (
b10 )
1%
#122
0%
#123
b11 &
b11 (
b11 )
1%
#124
0%
#125
b100 &
b100 (
b100 )
1%
#126
0%
#127
b101 &
b101 (
b101 )
1%
#128
0%
#129
b110 &
b110 (
b110 )
1%
#130
0%
#131
b111 &
b111 (
b111 )
1%
#132
0%
#133
b1000 &
b1000 (
b1000 )
1%
#134
0%
#135
b1001 &
b1001 (
b1001 )
1%
#136
0%
#137
b1010 &
b1010 (
b1010 )
1%
#138
0%
#139
b1011 &
b1011 (
b1011 )
1%
#140
0%
#141
b1100 &
b1100 (
b1100 )
1%
#142
0%
#143
b1101 &
b1101 (
b1101 )
1%
#144
0%
#145
b1110 &
b1110 (
b1110 )
1%
#146
0%
#147
b1111 &
b1111 (
b1111 )
1%
#148
0%
#149
b0 &
b0 (
b0 )
1%
#150
0%
#151
b1 &
b1 (
b1 )
1%
#152
0%
#153
b10 &
b10 (
b10 )
1%
#154
0%
#155
b11 &
b11 (
b11 )
1%
#156
0%
#157
b100 &
b100 (
b100 )
1%
#158
0%
#159
b101 &
b101 (
b101 )
1%
#160
0%
#161
b110 &
b110 (
b110 )
1%
#162
0%
#163
b111 &
b111 (
b111 )
1%
#164
0%
#165
b1000 &
b1000 (
b1000 )
1%
#166
0%
#167
b1001 &
b1001 (
b1001 )
1%
#168
0%
#169
1%
1"
0#
#170
0%
#171
1%
#172
0%
#173
1%
#174
0%
1#
#175
b0 &
b0 (
b0 )
1%
#176
0%
#177
1%
#178
0%
b110 $
b110 '
b110 *
#179
b110 &
b110 (
b110 )
1%
#180
0%
#181
1%
#182
0%
#183
b111 &
b111 (
b111 )
1%
0"
#184
0%
#185
b1000 &
b1000 (
b1000 )
1%
#186
0%
#187
b1001 &
b1001 (
b1001 )
1%
#188
0%
#189
b1010 &
b1010 (
b1010 )
1%
#190
0%
#191
b1011 &
b1011 (
b1011 )
1%
#192
0%
#193
b1100 &
b1100 (
b1100 )
1%
#194
0%
#195
b1101 &
b1101 (
b1101 )
1%
#196
0%
#197
b1110 &
b1110 (
b1110 )
1%
#198
0%
#199
b1111 &
b1111 (
b1111 )
1%
#200
0%
#201
b0 &
b0 (
b0 )
1%
#202
0%
#203
b1 &
b1 (
b1 )
1%
#204
0%
#205
b10 &
b10 (
b10 )
1%
#206
0%
#207
b11 &
b11 (
b11 )
1%
#208
0%
#209
b100 &
b100 (
b100 )
1%
#210
0%
#211
b101 &
b101 (
b101 )
1%
#212
0%
#213
1%
0#
